hotelagent/__init__.py
hotelagent-0.0.1.dist-info/METADATA
hotelagent-0.0.1.dist-info/WHEEL
hotelagent-0.0.1.dist-info/licenses/LICENSE
hotelagent-0.0.1.dist-info/RECORD
